ak_django_datadog-0.1.0.5.dist-info/DESCRIPTION.rst
ak_django_datadog-0.1.0.5.dist-info/METADATA
ak_django_datadog-0.1.0.5.dist-info/RECORD
ak_django_datadog-0.1.0.5.dist-info/WHEEL
ak_django_datadog-0.1.0.5.dist-info/metadata.json
ak_django_datadog-0.1.0.5.dist-info/top_level.txt
datadog/__init__.py
datadog/middleware/__init__.py
datadog/middleware/request_handler.py
