Metadata-Version: 2.0
Name: ak-django-datadog
Version: 0.1.0.5
Summary: Simple Django middleware for submitting timings and exceptions to Datadog.
Home-page: UNKNOWN
Author: Conor Branagan
Author-email: conor.branagan@gmail.com
License: BSD
Platform: UNKNOWN
